{"type": "FeatureCollection", "features": [{"type": "Feature", "properties": {"id": 8022, "lvl": 0, "eu": "F", "efta": "T", "cc": "F", "oth": "F", "co": "T"}, "geometry": {"type": "LineString", "coordinates": [[11.62, 78.465], [11.842, 78.438], [11.877, 78.388], [12.045, 78.294], [12.089, 78.239], [11.861, 78.239], [11.81, 78.261], [11.773, 78.305], [11.641, 78.348], [11.528, 78.396], [11.325, 78.445], [11.232, 78.451], [11.142, 78.445], [11.072, 78.46], [11.007, 78.503], [10.961, 78.555], [10.914, 78.587], [10.528, 78.779], [10.515, 78.801], [10.515, 78.846], [10.48, 78.892], [10.549, 78.896], [10.743, 78.882], [10.83, 78.869], [10.948, 78.84], [10.958, 78.825], [10.928, 78.807], [10.929, 78.79], [10.983, 78.771], [11.094, 78.761], [11.13, 78.745], [11.12, 78.731], [11.068, 78.719], [11.049, 78.697], [11.061, 78.673], [11.105, 78.655], [11.12, 78.623], [11.228, 78.608], [11.258, 78.579], [11.277, 78.545], [11.422, 78.541], [11.496, 78.504], [11.62, 78.465]]}}, {"type": "Feature", "properties": {"id": 8017, "lvl": 0, "eu": "F", "efta": "T", "cc": "F", "oth": "F", "co": "T"}, "geometry": {"type": "LineString", "coordinates": [[11.576, 78.733], [11.564, 78.728], [11.553, 78.733], [11.561, 78.741], [11.566, 78.741], [11.576, 78.733]]}}, {"type": "Feature", "properties": {"id": 8056, "lvl": 0, "eu": "F", "efta": "T", "cc": "F", "oth": "F", "co": "T"}, "geometry": {"type": "LineString", "coordinates": [[11.054, 79.679], [10.914, 79.646], [10.789, 79.65], [10.756, 79.666], [10.764, 79.692], [10.757, 79.712], [10.83, 79.726], [10.947, 79.722], [11.039, 79.692], [11.054, 79.679]]}}, {"type": "Feature", "properties": {"id": 8057, "lvl": 0, "eu": "F", "efta": "T", "cc": "F", "oth": "F", "co": "T"}, "geometry": {"type": "LineString", "coordinates": [[10.933, 79.754], [10.779, 79.734], [10.683, 79.761], [10.787, 79.788], [10.901, 79.773], [10.933, 79.754]]}}, {"type": "Feature", "properties": {"id": 8058, "lvl": 0, "eu": "F", "efta": "T", "cc": "F", "oth": "F", "co": "T"}, "geometry": {"type": "LineString", "coordinates": [[11.37, 79.807], [11.345, 79.79], [11.313, 79.801], [11.349, 79.815], [11.37, 79.807]]}}, {"type": "Feature", "properties": {"id": 8059, "lvl": 0, "eu": "F", "efta": "T", "cc": "F", "oth": "F", "co": "T"}, "geometry": {"type": "LineString", "coordinates": [[11.601, 79.857], [11.572, 79.828], [11.526, 79.833], [11.569, 79.861], [11.601, 79.857]]}}, {"type": "Feature", "properties": {"id": 8060, "lvl": 0, "eu": "F", "efta": "T", "cc": "F", "oth": "F", "co": "T"}, "geometry": {"type": "LineString", "coordinates": [[11.357, 79.842], [11.345, 79.838], [11.309, 79.84], [11.275, 79.846], [11.265, 79.85], [11.28, 79.858], [11.277, 79.867], [11.306, 79.868], [11.325, 79.863], [11.357, 79.842]]}}, {"type": "Feature", "properties": {"id": 8061, "lvl": 0, "eu": "F", "efta": "T", "cc": "F", "oth": "F", "co": "T"}, "geometry": {"type": "LineString", "coordinates": [[11.496, 79.858], [11.471, 79.841], [11.436, 79.853], [11.47, 79.871], [11.496, 79.858]]}}, {"type": "Feature", "properties": {"id": 8011, "lvl": 0, "eu": "F", "efta": "T", "cc": "F", "oth": "F", "co": "T"}, "geometry": {"type": "LineString", "coordinates": [[12.219, 78.541], [12.2, 78.538], [12.176, 78.552], [12.201, 78.557], [12.219, 78.541]]}}, {"type": "Feature", "properties": {"id": 8027, "lvl": 0, "eu": "F", "efta": "T", "cc": "F", "oth": "F", "co": "T"}, "geometry": {"type": "LineString", "coordinates": [[12.154, 78.969], [12.047, 78.96], [12.007, 78.966], [11.978, 78.982], [12.005, 78.995], [12.154, 79.001], [12.202, 78.982], [12.19, 78.972], [12.154, 78.969]]}}, {"type": "Feature", "properties": {"id": 7994, "lvl": 0, "eu": "F", "efta": "T", "cc": "F", "oth": "F", "co": "T"}, "geometry": {"type": "LineString", "coordinates": [[14.972, 77.052], [14.961, 77.049], [14.947, 77.058], [14.962, 77.063], [14.972, 77.052]]}}, {"type": "Feature", "properties": {"id": 7996, "lvl": 0, "eu": "F", "efta": "T", "cc": "F", "oth": "F", "co": "T"}, "geometry": {"type": "LineString", "coordinates": [[15.063, 77.08], [15.05, 77.075], [15.035, 77.082], [15.05, 77.089], [15.063, 77.08]]}}, {"type": "Feature", "properties": {"id": 8004, "lvl": 0, "eu": "F", "efta": "T", "cc": "F", "oth": "F", "co": "T"}, "geometry": {"type": "LineString", "coordinates": [[14.918, 77.594], [14.907, 77.592], [14.9, 77.597], [14.898, 77.602], [14.907, 77.605], [14.916, 77.603], [14.918, 77.594]]}}, {"type": "Feature", "properties": {"id": 8005, "lvl": 0, "eu": "F", "efta": "T", "cc": "F", "oth": "F", "co": "T"}, "geometry": {"type": "LineString", "coordinates": [[14.819, 77.684], [14.807, 77.676], [14.792, 77.681], [14.808, 77.689], [14.819, 77.684]]}}, {"type": "Feature", "properties": {"id": 8010, "lvl": 0, "eu": "F", "efta": "T", "cc": "F", "oth": "F", "co": "T"}, "geometry": {"type": "LineString", "coordinates": [[12.869, 78.32], [12.853, 78.314], [12.838, 78.322], [12.856, 78.328], [12.869, 78.32]]}}, {"type": "Feature", "properties": {"id": 8052, "lvl": 0, "eu": "F", "efta": "T", "cc": "F", "oth": "F", "co": "T"}, "geometry": {"type": "LineString", "coordinates": [[13.495, 79.616], [13.477, 79.599], [13.456, 79.603], [13.456, 79.609], [13.478, 79.621], [13.495, 79.616]]}}, {"type": "Feature", "properties": {"id": 8053, "lvl": 0, "eu": "F", "efta": "T", "cc": "F", "oth": "F", "co": "T"}, "geometry": {"type": "LineString", "coordinates": [[13.249, 79.678], [13.235, 79.667], [13.222, 79.672], [13.236, 79.681], [13.249, 79.678]]}}, {"type": "Feature", "properties": {"id": 8054, "lvl": 0, "eu": "F", "efta": "T", "cc": "F", "oth": "F", "co": "T"}, "geometry": {"type": "LineString", "coordinates": [[13.389, 79.68], [13.363, 79.664], [13.338, 79.671], [13.374, 79.686], [13.389, 79.68]]}}, {"type": "Feature", "properties": {"id": 8071, "lvl": 0, "eu": "F", "efta": "T", "cc": "F", "oth": "F", "co": "T"}, "geometry": {"type": "LineString", "coordinates": [[16.742, 79.894], [16.852, 79.874], [16.885, 79.877], [16.895, 79.886], [16.892, 79.927], [16.925, 79.943], [16.993, 79.953], [17.141, 79.95], [17.333, 79.932], [17.431, 79.902], [17.592, 79.88], [17.703, 79.845], [17.74, 79.815], [17.863, 79.794], [17.966, 79.756], [18.003, 79.73], [17.998, 79.7], [17.729, 79.593], [17.702, 79.552], [17.747, 79.522], [17.771, 79.443], [17.749, 79.419], [17.684, 79.386], [17.685, 79.379], [17.728, 79.373], [17.872, 79.404], [17.978, 79.448], [18.005, 79.468], [18.047, 79.543], [18.104, 79.588], [18.167, 79.608], [18.325, 79.61], [18.658, 79.551], [18.806, 79.452], [18.829, 79.426], [18.839, 79.4], [18.815, 79.314], [18.777, 79.292], [18.665, 79.266], [18.645, 79.247], [18.674, 79.238], [18.813, 79.236], [18.864, 79.225], [18.888, 79.196], [18.884, 79.149], [18.913, 79.129], [18.97, 79.12], [19.104, 79.123], [19.318, 79.179], [19.537, 79.143], [19.743, 79.143], [19.756, 79.133], [19.756, 79.058], [19.864, 79.046], [19.874, 79.034], [19.875, 79.009], [19.885, 79.002], [19.995, 78.988], [20.041, 78.983], [20.144, 79.002], [20.207, 78.997], [20.438, 78.951], [20.448, 78.942], [20.451, 78.912], [20.535, 78.884], [20.748, 78.906], [20.939, 78.898], [21.01, 78.885], [21.047, 78.862], [21.088, 78.851], [21.279, 78.836], [21.423, 78.837], [21.465, 78.821], [21.347, 78.726], [21.34, 78.711], [21.344, 78.687], [21.318, 78.674], [21.157, 78.675], [21.056, 78.66], [20.974, 78.677], [20.928, 78.699], [20.758, 78.707], [20.642, 78.7], [20.456, 78.72], [20.228, 78.699], [20.191, 78.683], [20.166, 78.658], [20.057, 78.639], [19.995, 78.61], [19.663, 78.611], [19.542, 78.586], [19.337, 78.563], [19.165, 78.571], [19.098, 78.543], [18.854, 78.513], [18.861, 78.5], [18.992, 78.443], [19.052, 78.371], [19.047, 78.346], [18.993, 78.333], [18.839, 78.343], [18.808, 78.335], [18.831, 78.317], [18.945, 78.279], [19.044, 78.231], [19.044, 78.215], [19.029, 78.206], [18.916, 78.182], [19.0, 78.128], [19.014, 78.111], [19.004, 78.096], [18.935, 78.06], [18.837, 78.042], [18.59, 78.051], [18.411, 78.025], [18.405, 78.012], [18.429, 77.983], [18.427, 77.96], [18.292, 77.896], [18.338, 77.874], [18.339, 77.846], [18.389, 77.815], [18.411, 77.76], [18.375, 77.727], [18.279, 77.702], [18.307, 77.632], [18.274, 77.554], [18.245, 77.524], [18.149, 77.503], [18.016, 77.508], [17.693, 77.562], [17.619, 77.541], [17.596, 77.509], [17.644, 77.488], [17.654, 77.471], [17.565, 77.421], [17.516, 77.405], [17.515, 77.394], [17.534, 77.375], [17.527, 77.361], [17.366, 77.276], [17.366, 77.26], [17.396, 77.23], [17.382, 77.208], [17.381, 77.179], [17.337, 77.15], [17.333, 77.116], [17.311, 77.082], [17.261, 77.056], [17.18, 77.054], [17.154, 77.043], [17.17, 77.021], [17.261, 76.98], [17.268, 76.967], [17.263, 76.956], [17.063, 76.87], [16.884, 76.838], [16.837, 76.806], [16.892, 76.77], [17.053, 76.755], [17.118, 76.724], [17.119, 76.704], [17.035, 76.642], [16.947, 76.604], [16.784, 76.572], [16.662, 76.564], [16.592, 76.572], [16.5, 76.605], [16.303, 76.57], [16.288, 76.59], [16.31, 76.656], [16.351, 76.681], [16.353, 76.698], [16.018, 76.744], [15.779, 76.804], [15.64, 76.851], [15.547, 76.867], [15.529, 76.879], [15.565, 76.907], [15.75, 76.94], [15.868, 76.943], [16.062, 76.971], [16.159, 76.966], [16.23, 76.938], [16.289, 76.933], [16.298, 76.94], [16.295, 76.96], [16.311, 76.969], [16.437, 76.979], [16.576, 76.979], [16.592, 77.0], [16.591, 77.021], [16.578, 77.031], [16.433, 77.051], [16.361, 77.029], [16.281, 77.029], [16.221, 77.004], [16.077, 77.028], [16.029, 77.065], [15.989, 77.077], [15.926, 77.062], [15.839, 77.063], [15.838, 77.05], [15.861, 77.03], [15.836, 77.017], [15.685, 77.004], [15.373, 77.002], [15.161, 77.039], [15.119, 77.077], [15.068, 77.104], [15.07, 77.117], [15.086, 77.136], [15.074, 77.146], [14.979, 77.157], [14.851, 77.158], [14.699, 77.2], [14.445, 77.186], [14.353, 77.217], [14.291, 77.273], [14.248, 77.283], [14.175, 77.298], [14.152, 77.318], [14.124, 77.345], [14.08, 77.373], [13.963, 77.42], [13.973, 77.444], [14.028, 77.464], [14.007, 77.477], [13.923, 77.49], [13.916, 77.499], [13.924, 77.518], [14.036, 77.545], [14.109, 77.562], [14.152, 77.564], [14.248, 77.571], [14.328, 77.576], [14.472, 77.568], [14.538, 77.544], [14.545, 77.526], [14.54, 77.501], [14.566, 77.492], [14.723, 77.495], [14.752, 77.507], [14.794, 77.542], [14.969, 77.56], [15.117, 77.543], [15.32, 77.538], [15.454, 77.524], [15.695, 77.529], [15.823, 77.517], [16.086, 77.447], [16.174, 77.412], [16.232, 77.407], [16.296, 77.435], [16.307, 77.465], [16.021, 77.514], [15.846, 77.563], [15.216, 77.606], [14.916, 77.614], [14.829, 77.653], [14.887, 77.678], [15.386, 77.731], [16.165, 77.773], [16.354, 77.803], [16.501, 77.797], [16.821, 77.806], [17.104, 77.77], [17.124, 77.777], [17.103, 77.789], [16.858, 77.833], [16.806, 77.864], [16.815, 77.878], [16.872, 77.881], [16.91, 77.897], [16.869, 77.921], [16.762, 77.906], [16.599, 77.857], [16.42, 77.85], [16.282, 77.856], [15.882, 77.83], [15.366, 77.867], [15.046, 77.799], [14.81, 77.787], [14.682, 77.77], [14.584, 77.778], [14.537, 77.761], [14.442, 77.754], [14.248, 77.761], [14.152, 77.765], [14.116, 77.766], [14.032, 77.757], [13.934, 77.729], [13.851, 77.74], [13.769, 77.739], [13.75, 77.745], [13.744, 77.756], [13.79, 77.788], [13.795, 77.806], [13.761, 77.825], [13.659, 77.852], [13.659, 77.893], [13.624, 77.94], [13.627, 77.997], [13.6, 78.051], [13.829, 78.093], [13.968, 78.091], [14.119, 78.033], [14.152, 78.016], [14.229, 77.979], [14.248, 77.976], [14.273, 77.972], [14.295, 77.984], [14.289, 78.012], [14.248, 78.039], [14.225, 78.054], [14.208, 78.089], [14.213, 78.095], [14.248, 78.098], [14.326, 78.104], [14.497, 78.101], [14.657, 78.111], [14.778, 78.118], [14.847, 78.111], [14.902, 78.105], [14.968, 78.106], [14.982, 78.111], [15.037, 78.156], [15.357, 78.239], [15.499, 78.246], [15.653, 78.227], [15.708, 78.23], [15.714, 78.24], [15.653, 78.263], [15.618, 78.295], [15.667, 78.318], [15.825, 78.346], [16.124, 78.361], [16.461, 78.338], [16.817, 78.341], [17.082, 78.389], [17.311, 78.418], [17.337, 78.433], [17.3, 78.447], [17.202, 78.444], [16.806, 78.393], [16.64, 78.413], [16.545, 78.438], [16.437, 78.44], [16.398, 78.449], [16.409, 78.483], [16.587, 78.585], [16.722, 78.63], [16.901, 78.651], [16.868, 78.67], [16.661, 78.679], [16.539, 78.709], [16.488, 78.701], [16.419, 78.666], [16.35, 78.602], [16.255, 78.559], [16.053, 78.527], [15.929, 78.487], [15.598, 78.461], [15.414, 78.47], [15.286, 78.513], [15.256, 78.537], [15.231, 78.573], [15.258, 78.604], [15.403, 78.631], [15.469, 78.698], [15.477, 78.739], [15.444, 78.776], [15.426, 78.813], [15.392, 78.832], [15.357, 78.836], [15.268, 78.817], [15.194, 78.766], [15.178, 78.729], [15.177, 78.661], [15.019, 78.632], [14.954, 78.606], [14.805, 78.64], [14.8, 78.649], [14.815, 78.674], [14.812, 78.695], [14.79, 78.719], [14.75, 78.733], [14.65, 78.735], [14.595, 78.707], [14.514, 78.691], [14.319, 78.712], [14.319, 78.703], [14.339, 78.692], [14.5, 78.646], [14.54, 78.573], [14.493, 78.549], [14.333, 78.544], [14.326, 78.534], [14.339, 78.509], [14.319, 78.482], [14.576, 78.455], [14.669, 78.423], [14.694, 78.408], [14.699, 78.396], [14.611, 78.381], [14.474, 78.387], [14.39, 78.38], [14.248, 78.398], [14.152, 78.411], [14.109, 78.417], [14.094, 78.403], [14.138, 78.376], [14.136, 78.353], [14.152, 78.35], [14.236, 78.334], [14.248, 78.328], [14.26, 78.322], [14.264, 78.309], [14.248, 78.3], [14.085, 78.265], [14.018, 78.287], [13.922, 78.294], [13.913, 78.287], [13.913, 78.262], [13.904, 78.25], [13.803, 78.252], [13.798, 78.224], [13.762, 78.208], [13.458, 78.208], [13.156, 78.227], [12.981, 78.218], [12.929, 78.245], [12.906, 78.302], [12.851, 78.349], [12.595, 78.391], [12.469, 78.434], [12.418, 78.461], [12.399, 78.483], [12.424, 78.494], [12.505, 78.501], [12.809, 78.501], [13.119, 78.515], [13.224, 78.543], [13.239, 78.561], [13.118, 78.572], [13.021, 78.544], [12.811, 78.529], [12.474, 78.541], [12.418, 78.554], [12.425, 78.579], [12.402, 78.591], [12.16, 78.597], [11.989, 78.618], [11.908, 78.639], [11.86, 78.666], [11.866, 78.682], [11.904, 78.696], [11.905, 78.705], [11.743, 78.711], [11.654, 78.728], [11.635, 78.741], [11.656, 78.77], [11.721, 78.803], [11.835, 78.821], [11.847, 78.835], [11.796, 78.85], [11.568, 78.879], [11.398, 78.926], [11.371, 78.946], [11.39, 78.957], [11.544, 78.967], [11.813, 78.948], [11.996, 78.917], [12.445, 78.876], [12.56, 78.911], [12.551, 78.919], [12.493, 78.92], [12.462, 78.934], [12.464, 78.956], [12.505, 78.976], [12.486, 78.99], [12.162, 79.016], [11.972, 79.012], [11.723, 79.074], [11.73, 79.087], [11.756, 79.098], [11.843, 79.119], [11.861, 79.156], [11.909, 79.187], [12.085, 79.204], [12.062, 79.231], [12.091, 79.265], [12.081, 79.294], [11.864, 79.282], [11.843, 79.268], [11.833, 79.239], [11.811, 79.231], [11.759, 79.249], [11.718, 79.29], [11.722, 79.31], [11.754, 79.328], [11.748, 79.338], [11.632, 79.348], [11.524, 79.335], [11.511, 79.318], [11.543, 79.276], [11.649, 79.209], [11.653, 79.191], [11.643, 79.175], [11.529, 79.136], [11.408, 79.113], [11.292, 79.11], [11.228, 79.118], [11.178, 79.144], [11.101, 79.236], [10.99, 79.304], [10.914, 79.324], [10.875, 79.346], [10.885, 79.405], [10.939, 79.439], [10.94, 79.463], [10.838, 79.497], [10.734, 79.515], [10.692, 79.544], [10.705, 79.553], [10.736, 79.557], [10.937, 79.547], [11.021, 79.556], [11.017, 79.566], [10.917, 79.585], [10.892, 79.599], [10.923, 79.622], [10.999, 79.637], [11.437, 79.619], [11.481, 79.625], [11.478, 79.632], [11.303, 79.667], [11.215, 79.708], [11.197, 79.735], [11.226, 79.772], [11.25, 79.779], [11.36, 79.777], [11.498, 79.756], [11.52, 79.767], [11.54, 79.802], [11.649, 79.826], [11.789, 79.829], [11.827, 79.792], [11.902, 79.772], [11.93, 79.742], [11.983, 79.718], [12.054, 79.668], [12.096, 79.666], [12.131, 79.687], [12.156, 79.691], [12.184, 79.681], [12.208, 79.654], [12.23, 79.648], [12.282, 79.662], [12.299, 79.685], [12.27, 79.721], [12.193, 79.759], [12.173, 79.777], [12.18, 79.793], [12.241, 79.831], [12.362, 79.829], [12.432, 79.793], [12.574, 79.763], [12.829, 79.78], [13.035, 79.817], [13.743, 79.873], [13.843, 79.857], [13.915, 79.808], [13.913, 79.787], [13.838, 79.737], [13.695, 79.697], [13.436, 79.695], [13.25, 79.705], [13.035, 79.692], [12.928, 79.659], [12.626, 79.595], [12.392, 79.583], [12.385, 79.576], [12.388, 79.536], [12.445, 79.515], [12.548, 79.52], [12.736, 79.568], [12.809, 79.564], [13.151, 79.592], [13.403, 79.575], [13.427, 79.558], [13.344, 79.526], [13.269, 79.51], [13.242, 79.471], [13.399, 79.438], [13.421, 79.443], [13.432, 79.467], [13.456, 79.477], [13.539, 79.477], [13.635, 79.456], [13.857, 79.369], [13.876, 79.34], [13.875, 79.296], [13.933, 79.283], [14.041, 79.295], [14.09, 79.347], [14.063, 79.374], [13.996, 79.401], [13.966, 79.452], [13.89, 79.488], [13.861, 79.524], [13.864, 79.543], [13.908, 79.569], [14.01, 79.595], [14.167, 79.611], [14.171, 79.619], [14.161, 79.642], [14.219, 79.659], [14.248, 79.688], [14.471, 79.788], [14.545, 79.797], [14.767, 79.777], [14.924, 79.731], [15.096, 79.641], [15.212, 79.604], [15.236, 79.533], [15.316, 79.501], [15.362, 79.468], [15.435, 79.356], [15.609, 79.27], [15.707, 79.236], [15.7, 79.208], [15.616, 79.151], [15.618, 79.128], [15.64, 79.105], [15.695, 79.094], [15.718, 79.126], [15.747, 79.144], [15.783, 79.153], [15.853, 79.151], [15.982, 79.098], [16.098, 79.01], [16.186, 78.961], [16.397, 78.894], [16.47, 78.9], [16.488, 78.92], [16.463, 78.951], [16.38, 78.979], [16.258, 79.085], [16.171, 79.136], [16.087, 79.227], [15.955, 79.302], [15.86, 79.501], [15.85, 79.553], [15.81, 79.591], [15.788, 79.631], [15.736, 79.653], [15.7, 79.689], [15.63, 79.808], [15.635, 79.836], [15.648, 79.851], [15.707, 79.871], [16.073, 79.87], [16.061, 79.887], [15.962, 79.921], [15.951, 79.951], [16.031, 80.006], [16.168, 80.046], [16.255, 80.058], [16.522, 80.035], [16.599, 79.976], [16.676, 79.948], [16.687, 79.918], [16.742, 79.894]]}}, {"type": "Feature", "properties": {"id": 8013, "lvl": 0, "eu": "F", "efta": "T", "cc": "F", "oth": "F", "co": "T"}, "geometry": {"type": "LineString", "coordinates": [[14.599, 78.647], [14.588, 78.638], [14.567, 78.643], [14.584, 78.653], [14.599, 78.647]]}}, {"type": "Feature", "properties": {"id": 8016, "lvl": 0, "eu": "F", "efta": "T", "cc": "F", "oth": "F", "co": "T"}, "geometry": {"type": "LineString", "coordinates": [[14.746, 78.68], [14.706, 78.666], [14.668, 78.674], [14.676, 78.69], [14.698, 78.696], [14.732, 78.691], [14.746, 78.68]]}}, {"type": "Feature", "properties": {"id": 8033, "lvl": 0, "eu": "F", "efta": "T", "cc": "F", "oth": "F", "co": "T"}, "geometry": {"type": "LineString", "coordinates": [[16.09, 79.045], [16.079, 79.038], [16.068, 79.047], [16.081, 79.055], [16.09, 79.045]]}}, {"type": "Feature", "properties": {"id": 8036, "lvl": 0, "eu": "F", "efta": "T", "cc": "F", "oth": "F", "co": "T"}, "geometry": {"type": "LineString", "coordinates": [[15.744, 79.204], [15.732, 79.2], [15.717, 79.208], [15.73, 79.214], [15.744, 79.204]]}}, {"type": "Feature", "properties": {"id": 8069, "lvl": 0, "eu": "F", "efta": "T", "cc": "F", "oth": "F", "co": "T"}, "geometry": {"type": "LineString", "coordinates": [[14.514, 80.036], [14.475, 80.004], [14.435, 80.017], [14.487, 80.043], [14.514, 80.036]]}}, {"type": "Feature", "properties": {"id": 7993, "lvl": 0, "eu": "F", "efta": "T", "cc": "F", "oth": "F", "co": "T"}, "geometry": {"type": "LineString", "coordinates": [[21.958, 76.997], [21.944, 76.992], [21.929, 76.998], [21.946, 77.005], [21.958, 76.997]]}}, {"type": "Feature", "properties": {"id": 7995, "lvl": 0, "eu": "F", "efta": "T", "cc": "F", "oth": "F", "co": "T"}, "geometry": {"type": "LineString", "coordinates": [[22.472, 77.072], [22.461, 77.063], [22.445, 77.07], [22.459, 77.077], [22.472, 77.072]]}}, {"type": "Feature", "properties": {"id": 7998, "lvl": 0, "eu": "F", "efta": "T", "cc": "F", "oth": "F", "co": "T"}, "geometry": {"type": "LineString", "coordinates": [[22.019, 77.22], [22.003, 77.214], [21.981, 77.223], [22.003, 77.229], [22.019, 77.22]]}}, {"type": "Feature", "properties": {"id": 8002, "lvl": 0, "eu": "F", "efta": "T", "cc": "F", "oth": "F", "co": "T"}, "geometry": {"type": "LineString", "coordinates": [[22.487, 77.391], [22.474, 77.382], [22.459, 77.387], [22.473, 77.395], [22.487, 77.391]]}}, {"type": "Feature", "properties": {"id": 8003, "lvl": 0, "eu": "F", "efta": "T", "cc": "F", "oth": "F", "co": "T"}, "geometry": {"type": "LineString", "coordinates": [[22.437, 77.397], [22.412, 77.377], [22.379, 77.386], [22.41, 77.403], [22.437, 77.397]]}}, {"type": "Feature", "properties": {"id": 8000, "lvl": 0, "eu": "F", "efta": "T", "cc": "F", "oth": "F", "co": "T"}, "geometry": {"type": "LineString", "coordinates": [[21.39, 77.274], [21.377, 77.272], [21.363, 77.283], [21.377, 77.286], [21.39, 77.274]]}}, {"type": "Feature", "properties": {"id": 8008, "lvl": 0, "eu": "F", "efta": "T", "cc": "F", "oth": "F", "co": "T"}, "geometry": {"type": "LineString", "coordinates": [[20.46, 78.209], [20.449, 78.201], [20.431, 78.209], [20.447, 78.215], [20.46, 78.209]]}}, {"type": "Feature", "properties": {"id": 8014, "lvl": 0, "eu": "F", "efta": "T", "cc": "F", "oth": "F", "co": "T"}, "geometry": {"type": "LineString", "coordinates": [[21.434, 78.577], [21.548, 78.552], [21.705, 78.562], [21.775, 78.58], [21.942, 78.57], [22.115, 78.465], [22.167, 78.401], [22.18, 78.359], [22.169, 78.327], [22.138, 78.297], [22.028, 78.262], [21.734, 78.265], [21.257, 78.231], [21.062, 78.208], [20.827, 78.227], [20.715, 78.215], [20.705, 78.229], [20.736, 78.271], [20.725, 78.303], [20.733, 78.331], [20.674, 78.354], [20.623, 78.399], [20.543, 78.436], [20.237, 78.492], [20.33, 78.517], [21.014, 78.562], [21.07, 78.579], [21.122, 78.615], [21.201, 78.655], [21.23, 78.66], [21.277, 78.648], [21.434, 78.577]]}}, {"type": "Feature", "properties": {"id": 8012, "lvl": 0, "eu": "F", "efta": "T", "cc": "F", "oth": "F", "co": "T"}, "geometry": {"type": "LineString", "coordinates": [[20.145, 78.628], [20.133, 78.621], [20.118, 78.628], [20.133, 78.634], [20.145, 78.628]]}}, {"type": "Feature", "properties": {"id": 8015, "lvl": 0, "eu": "F", "efta": "T", "cc": "F", "oth": "F", "co": "T"}, "geometry": {"type": "LineString", "coordinates": [[20.627, 78.689], [20.615, 78.678], [20.601, 78.684], [20.616, 78.692], [20.627, 78.689]]}}, {"type": "Feature", "properties": {"id": 8025, "lvl": 0, "eu": "F", "efta": "T", "cc": "F", "oth": "F", "co": "T"}, "geometry": {"type": "LineString", "coordinates": [[21.662, 78.975], [21.641, 78.969], [21.617, 78.984], [21.644, 78.99], [21.662, 78.975]]}}, {"type": "Feature", "properties": {"id": 8028, "lvl": 0, "eu": "F", "efta": "T", "cc": "F", "oth": "F", "co": "T"}, "geometry": {"type": "LineString", "coordinates": [[20.963, 78.998], [20.952, 78.995], [20.937, 79.005], [20.95, 79.009], [20.963, 78.998]]}}, {"type": "Feature", "properties": {"id": 8029, "lvl": 0, "eu": "F", "efta": "T", "cc": "F", "oth": "F", "co": "T"}, "geometry": {"type": "LineString", "coordinates": [[20.895, 79.011], [20.886, 79.0], [20.871, 79.004], [20.883, 79.013], [20.895, 79.011]]}}, {"type": "Feature", "properties": {"id": 7989, "lvl": 0, "eu": "F", "efta": "T", "cc": "F", "oth": "F", "co": "T"}, "geometry": {"type": "LineString", "coordinates": [[19.144, 74.356], [19.06, 74.338], [18.97, 74.379], [18.824, 74.426], [18.76, 74.472], [18.784, 74.49], [18.822, 74.497], [19.091, 74.513], [19.142, 74.507], [19.16, 74.497], [19.173, 74.489], [19.26, 74.46], [19.246, 74.428], [19.184, 74.4], [19.168, 74.37], [19.144, 74.356]]}}, {"type": "Feature", "properties": {"id": 7990, "lvl": 0, "eu": "F", "efta": "T", "cc": "F", "oth": "F", "co": "T"}, "geometry": {"type": "LineString", "coordinates": [[16.594, 76.474], [16.558, 76.467], [16.468, 76.517], [16.493, 76.522], [16.554, 76.504], [16.594, 76.474]]}}, {"type": "Feature", "properties": {"id": 7992, "lvl": 0, "eu": "F", "efta": "T", "cc": "F", "oth": "F", "co": "T"}, "geometry": {"type": "LineString", "coordinates": [[16.975, 76.829], [16.961, 76.825], [16.949, 76.832], [16.964, 76.838], [16.975, 76.829]]}}, {"type": "Feature", "properties": {"id": 8037, "lvl": 0, "eu": "F", "efta": "T", "cc": "F", "oth": "F", "co": "T"}, "geometry": {"type": "LineString", "coordinates": [[19.462, 79.218], [19.447, 79.211], [19.417, 79.222], [19.447, 79.228], [19.462, 79.218]]}}, {"type": "Feature", "properties": {"id": 8041, "lvl": 0, "eu": "F", "efta": "T", "cc": "F", "oth": "F", "co": "T"}, "geometry": {"type": "LineString", "coordinates": [[19.72, 79.297], [19.706, 79.288], [19.684, 79.293], [19.705, 79.303], [19.72, 79.297]]}}, {"type": "Feature", "properties": {"id": 7991, "lvl": 0, "eu": "F", "efta": "T", "cc": "F", "oth": "F", "co": "T"}, "geometry": {"type": "LineString", "coordinates": [[25.004, 76.498], [24.933, 76.448], [24.883, 76.448], [24.93, 76.492], [25.015, 76.539], [25.216, 76.612], [25.386, 76.687], [25.405, 76.687], [25.357, 76.644], [25.237, 76.603], [25.124, 76.544], [25.004, 76.498]]}}, {"type": "Feature", "properties": {"id": 8006, "lvl": 0, "eu": "F", "efta": "T", "cc": "F", "oth": "F", "co": "T"}, "geometry": {"type": "LineString", "coordinates": [[25.135, 77.795], [25.123, 77.787], [25.106, 77.794], [25.123, 77.801], [25.135, 77.795]]}}, {"type": "Feature", "properties": {"id": 7997, "lvl": 0, "eu": "F", "efta": "T", "cc": "F", "oth": "F", "co": "T"}, "geometry": {"type": "LineString", "coordinates": [[22.847, 77.151], [22.832, 77.147], [22.814, 77.158], [22.834, 77.163], [22.847, 77.151]]}}, {"type": "Feature", "properties": {"id": 7999, "lvl": 0, "eu": "F", "efta": "T", "cc": "F", "oth": "F", "co": "T"}, "geometry": {"type": "LineString", "coordinates": [[23.141, 77.276], [23.094, 77.253], [23.054, 77.263], [23.096, 77.285], [23.141, 77.276]]}}, {"type": "Feature", "properties": {"id": 8001, "lvl": 0, "eu": "F", "efta": "T", "cc": "F", "oth": "F", "co": "T"}, "geometry": {"type": "LineString", "coordinates": [[23.255, 77.291], [23.244, 77.283], [23.222, 77.292], [23.242, 77.3], [23.255, 77.291]]}}, {"type": "Feature", "properties": {"id": 8082, "lvl": 0, "eu": "F", "efta": "T", "cc": "F", "oth": "F", "co": "T"}, "geometry": {"type": "LineString", "coordinates": [[24.762, 80.341], [24.75, 80.341], [24.73, 80.356], [24.747, 80.359], [24.762, 80.341]]}}, {"type": "Feature", "properties": {"id": 8085, "lvl": 0, "eu": "F", "efta": "T", "cc": "F", "oth": "F", "co": "T"}, "geometry": {"type": "LineString", "coordinates": [[24.322, 80.376], [24.283, 80.37], [24.234, 80.375], [24.141, 80.38], [24.106, 80.388], [24.114, 80.402], [24.137, 80.417], [24.151, 80.434], [24.187, 80.441], [24.218, 80.44], [24.268, 80.429], [24.287, 80.415], [24.346, 80.389], [24.322, 80.376]]}}, {"type": "Feature", "properties": {"id": 8089, "lvl": 0, "eu": "F", "efta": "T", "cc": "F", "oth": "F", "co": "T"}, "geometry": {"type": "LineString", "coordinates": [[24.123, 80.472], [24.09, 80.459], [24.034, 80.481], [24.086, 80.494], [24.123, 80.472]]}}, {"type": "Feature", "properties": {"id": 8009, "lvl": 0, "eu": "F", "efta": "T", "cc": "F", "oth": "F", "co": "T"}, "geometry": {"type": "LineString", "coordinates": [[23.109, 78.201], [23.15, 78.165], [23.143, 78.146], [23.106, 78.111], [23.12, 78.08], [23.147, 78.054], [23.274, 78.004], [23.303, 77.981], [23.394, 77.967], [23.516, 77.925], [23.661, 77.914], [24.045, 77.942], [24.13, 77.939], [24.229, 77.921], [24.21, 77.892], [24.139, 77.857], [24.093, 77.795], [24.159, 77.75], [24.165, 77.737], [24.156, 77.727], [24.103, 77.703], [23.989, 77.684], [23.95, 77.63], [23.83, 77.576], [23.672, 77.508], [23.397, 77.42], [23.362, 77.414], [23.125, 77.37], [22.992, 77.302], [22.788, 77.279], [22.657, 77.245], [22.579, 77.257], [22.551, 77.281], [22.568, 77.3], [22.653, 77.331], [22.685, 77.359], [22.675, 77.38], [22.619, 77.397], [22.619, 77.415], [22.646, 77.42], [22.715, 77.434], [22.756, 77.461], [22.75, 77.481], [22.699, 77.506], [22.695, 77.516], [23.018, 77.535], [23.037, 77.543], [23.037, 77.555], [23.029, 77.571], [23.008, 77.579], [22.896, 77.572], [22.733, 77.578], [22.659, 77.543], [22.635, 77.573], [22.615, 77.585], [22.52, 77.605], [22.432, 77.607], [22.348, 77.587], [22.048, 77.544], [21.955, 77.514], [21.822, 77.502], [21.516, 77.499], [21.07, 77.445], [20.857, 77.452], [20.846, 77.469], [20.858, 77.505], [20.85, 77.534], [20.883, 77.567], [20.927, 77.587], [21.04, 77.592], [21.136, 77.615], [21.168, 77.652], [21.183, 77.704], [21.209, 77.737], [21.345, 77.814], [21.46, 77.856], [21.522, 77.92], [21.494, 77.941], [21.226, 77.976], [21.121, 78.012], [20.961, 78.042], [20.851, 78.073], [20.825, 78.094], [20.861, 78.119], [21.062, 78.151], [21.518, 78.197], [21.731, 78.213], [22.065, 78.199], [22.346, 78.208], [22.469, 78.236], [22.823, 78.252], [23.109, 78.201]]}}, {"type": "Feature", "properties": {"id": 8024, "lvl": 0, "eu": "F", "efta": "T", "cc": "F", "oth": "F", "co": "T"}, "geometry": {"type": "LineString", "coordinates": [[21.786, 78.98], [21.768, 78.972], [21.746, 78.981], [21.769, 78.989], [21.786, 78.98]]}}, {"type": "Feature", "properties": {"id": 8090, "lvl": 0, "eu": "F", "efta": "T", "cc": "F", "oth": "F", "co": "T"}, "geometry": {"type": "LineString", "coordinates": [[19.995, 80.449], [20.09, 80.402], [20.237, 80.407], [20.368, 80.392], [20.485, 80.345], [20.526, 80.304], [20.561, 80.286], [20.77, 80.29], [20.793, 80.271], [20.81, 80.225], [20.851, 80.205], [21.005, 80.213], [21.145, 80.206], [21.292, 80.233], [21.34, 80.21], [21.45, 80.251], [21.641, 80.228], [21.665, 80.234], [21.698, 80.257], [21.78, 80.259], [21.82, 80.234], [21.805, 80.201], [21.672, 80.122], [21.697, 80.118], [21.819, 80.133], [22.019, 80.109], [22.158, 80.042], [22.203, 80.002], [22.233, 79.991], [22.283, 79.999], [22.334, 80.02], [22.45, 80.014], [22.456, 80.035], [22.476, 80.047], [22.418, 80.105], [22.403, 80.146], [22.454, 80.211], [22.472, 80.265], [22.503, 80.295], [22.375, 80.337], [22.356, 80.356], [22.36, 80.38], [22.436, 80.41], [22.583, 80.412], [22.616, 80.396], [22.642, 80.349], [22.711, 80.332], [22.728, 80.357], [22.788, 80.389], [22.81, 80.412], [22.807, 80.442], [22.78, 80.478], [22.801, 80.494], [22.984, 80.465], [23.218, 80.444], [23.282, 80.421], [23.27, 80.402], [23.183, 80.374], [23.215, 80.348], [23.273, 80.329], [23.264, 80.281], [23.23, 80.263], [23.07, 80.232], [23.019, 80.178], [23.018, 80.16], [23.039, 80.138], [23.098, 80.12], [23.139, 80.126], [23.169, 80.154], [23.233, 80.165], [23.375, 80.142], [23.391, 80.178], [23.424, 80.188], [23.472, 80.176], [23.533, 80.128], [23.603, 80.128], [23.675, 80.162], [23.741, 80.18], [23.739, 80.215], [23.752, 80.259], [23.77, 80.271], [23.947, 80.259], [24.001, 80.288], [24.183, 80.256], [24.192, 80.26], [24.205, 80.285], [24.331, 80.291], [24.316, 80.315], [24.198, 80.344], [24.207, 80.354], [24.437, 80.351], [24.529, 80.32], [24.517, 80.303], [24.441, 80.274], [24.443, 80.262], [24.462, 80.255], [24.697, 80.287], [24.775, 80.321], [24.828, 80.332], [24.852, 80.315], [24.828, 80.26], [24.847, 80.244], [25.02, 80.242], [25.252, 80.262], [25.265, 80.257], [25.271, 80.237], [25.299, 80.227], [25.475, 80.222], [25.587, 80.194], [25.667, 80.203], [25.763, 80.194], [25.771, 80.187], [25.763, 80.168], [25.784, 80.159], [25.912, 80.159], [26.096, 80.175], [26.318, 80.175], [26.736, 80.154], [26.883, 80.135], [27.003, 80.086], [27.148, 80.077], [27.184, 80.065], [27.186, 80.046], [27.149, 80.014], [27.135, 79.949], [27.159, 79.917], [27.219, 79.862], [27.206, 79.844], [27.177, 79.833], [26.934, 79.784], [26.75, 79.763], [26.616, 79.705], [26.216, 79.637], [25.746, 79.571], [25.724, 79.56], [25.719, 79.549], [25.781, 79.501], [25.782, 79.481], [25.764, 79.466], [25.364, 79.369], [25.075, 79.337], [24.883, 79.351], [24.337, 79.305], [24.133, 79.272], [24.053, 79.229], [23.957, 79.202], [23.566, 79.198], [23.358, 79.211], [23.123, 79.238], [22.865, 79.251], [22.762, 79.279], [22.726, 79.303], [22.725, 79.316], [22.737, 79.328], [22.821, 79.362], [22.799, 79.376], [22.271, 79.382], [21.789, 79.35], [21.37, 79.371], [20.968, 79.354], [20.791, 79.363], [20.763, 79.373], [20.738, 79.4], [20.705, 79.411], [20.078, 79.464], [19.995, 79.492], [19.958, 79.506], [19.771, 79.546], [19.723, 79.568], [19.685, 79.601], [19.702, 79.611], [19.753, 79.617], [19.995, 79.622], [20.147, 79.625], [20.239, 79.616], [20.438, 79.575], [20.818, 79.564], [21.003, 79.544], [21.135, 79.54], [21.151, 79.548], [20.893, 79.599], [20.646, 79.616], [20.591, 79.63], [20.575, 79.645], [20.967, 79.692], [21.347, 79.705], [21.622, 79.698], [21.713, 79.708], [21.753, 79.732], [21.673, 79.77], [21.617, 79.78], [21.578, 79.81], [21.418, 79.817], [21.2, 79.802], [20.689, 79.798], [20.559, 79.784], [20.447, 79.787], [19.995, 79.751], [19.641, 79.742], [19.534, 79.725], [19.465, 79.749], [19.398, 79.761], [18.981, 79.764], [18.892, 79.751], [18.84, 79.724], [18.764, 79.722], [18.745, 79.733], [18.731, 79.763], [18.678, 79.788], [18.638, 79.795], [18.581, 79.786], [18.445, 79.793], [18.285, 79.839], [18.177, 79.903], [18.262, 79.937], [18.58, 79.956], [18.69, 79.979], [18.773, 79.977], [18.796, 80.005], [18.846, 80.017], [18.85, 80.028], [18.525, 80.039], [18.254, 80.037], [18.145, 80.051], [18.009, 80.113], [17.933, 80.119], [17.839, 80.149], [17.857, 80.16], [17.981, 80.178], [18.217, 80.173], [18.434, 80.185], [18.674, 80.164], [18.778, 80.196], [18.895, 80.182], [19.055, 80.131], [19.326, 80.088], [19.371, 80.102], [19.411, 80.138], [19.449, 80.152], [19.293, 80.172], [19.202, 80.193], [19.077, 80.262], [19.036, 80.329], [19.085, 80.343], [19.232, 80.33], [19.344, 80.301], [19.447, 80.257], [19.538, 80.231], [19.632, 80.217], [19.725, 80.22], [19.735, 80.251], [19.768, 80.279], [19.78, 80.324], [19.815, 80.37], [19.699, 80.389], [19.506, 80.39], [19.46, 80.417], [19.462, 80.44], [19.508, 80.456], [19.662, 80.438], [19.662, 80.447], [19.628, 80.48], [19.637, 80.492], [19.661, 80.497], [19.834, 80.461], [19.973, 80.457], [19.995, 80.449]]}}, {"type": "Feature", "properties": {"id": 8072, "lvl": 0, "eu": "F", "efta": "T", "cc": "F", "oth": "F", "co": "T"}, "geometry": {"type": "LineString", "coordinates": [[22.341, 80.05], [22.313, 80.04], [22.284, 80.054], [22.321, 80.062], [22.341, 80.05]]}}, {"type": "Feature", "properties": {"id": 8073, "lvl": 0, "eu": "F", "efta": "T", "cc": "F", "oth": "F", "co": "T"}, "geometry": {"type": "LineString", "coordinates": [[22.037, 80.139], [22.02, 80.123], [21.995, 80.128], [22.017, 80.141], [22.037, 80.139]]}}, {"type": "Feature", "properties": {"id": 8075, "lvl": 0, "eu": "F", "efta": "T", "cc": "F", "oth": "F", "co": "T"}, "geometry": {"type": "LineString", "coordinates": [[22.342, 80.147], [22.328, 80.14], [22.312, 80.146], [22.328, 80.153], [22.342, 80.147]]}}, {"type": "Feature", "properties": {"id": 8007, "lvl": 0, "eu": "F", "efta": "T", "cc": "F", "oth": "F", "co": "T"}, "geometry": {"type": "LineString", "coordinates": [[25.08, 77.813], [25.069, 77.807], [25.053, 77.813], [25.069, 77.82], [25.08, 77.813]]}}, {"type": "Feature", "properties": {"id": 8020, "lvl": 0, "eu": "F", "efta": "T", "cc": "F", "oth": "F", "co": "T"}, "geometry": {"type": "LineString", "coordinates": [[26.952, 78.666], [26.74, 78.645], [26.721, 78.675], [26.502, 78.72], [26.358, 78.798], [26.392, 78.815], [26.475, 78.831], [26.572, 78.834], [26.621, 78.823], [26.691, 78.783], [26.848, 78.736], [27.011, 78.703], [26.984, 78.678], [26.952, 78.666]]}}, {"type": "Feature", "properties": {"id": 8018, "lvl": 0, "eu": "F", "efta": "T", "cc": "F", "oth": "F", "co": "T"}, "geometry": {"type": "LineString", "coordinates": [[28.633, 78.769], [28.621, 78.761], [28.607, 78.767], [28.622, 78.775], [28.633, 78.769]]}}, {"type": "Feature", "properties": {"id": 8019, "lvl": 0, "eu": "F", "efta": "T", "cc": "F", "oth": "F", "co": "T"}, "geometry": {"type": "LineString", "coordinates": [[28.672, 78.787], [28.654, 78.782], [28.625, 78.797], [28.651, 78.803], [28.672, 78.787]]}}, {"type": "Feature", "properties": {"id": 8021, "lvl": 0, "eu": "F", "efta": "T", "cc": "F", "oth": "F", "co": "T"}, "geometry": {"type": "LineString", "coordinates": [[28.768, 78.882], [28.756, 78.875], [28.74, 78.88], [28.757, 78.888], [28.768, 78.882]]}}, {"type": "Feature", "properties": {"id": 8023, "lvl": 0, "eu": "F", "efta": "T", "cc": "F", "oth": "F", "co": "T"}, "geometry": {"type": "LineString", "coordinates": [[28.979, 78.92], [29.137, 78.905], [29.316, 78.903], [29.544, 78.916], [29.577, 78.903], [29.557, 78.891], [29.363, 78.876], [29.243, 78.847], [29.13, 78.861], [28.966, 78.896], [28.749, 78.915], [28.607, 78.891], [28.501, 78.892], [28.373, 78.88], [28.1, 78.83], [27.91, 78.846], [27.881, 78.857], [28.151, 78.913], [28.385, 78.927], [28.442, 78.954], [28.477, 78.96], [28.871, 78.956], [28.979, 78.92]]}}, {"type": "Feature", "properties": {"id": 8026, "lvl": 0, "eu": "F", "efta": "T", "cc": "F", "oth": "F", "co": "T"}, "geometry": {"type": "LineString", "coordinates": [[30.205, 78.972], [30.16, 78.959], [30.072, 78.973], [30.036, 78.995], [30.223, 78.996], [30.205, 78.972]]}}, {"type": "Feature", "properties": {"id": 8074, "lvl": 0, "eu": "F", "efta": "T", "cc": "F", "oth": "F", "co": "T"}, "geometry": {"type": "LineString", "coordinates": [[28.158, 80.053], [28.034, 80.048], [27.937, 80.067], [27.868, 80.114], [27.887, 80.124], [27.986, 80.142], [28.063, 80.124], [28.245, 80.111], [28.252, 80.107], [28.246, 80.095], [28.253, 80.087], [28.217, 80.08], [28.205, 80.067], [28.158, 80.053]]}}, {"type": "Feature", "properties": {"id": 8080, "lvl": 0, "eu": "F", "efta": "T", "cc": "F", "oth": "F", "co": "T"}, "geometry": {"type": "LineString", "coordinates": [[32.0, 80.061], [31.707, 80.038], [31.542, 80.053], [31.425, 80.084], [31.448, 80.108], [31.505, 80.146], [31.626, 80.183], [31.904, 80.218], [32.032, 80.238], [32.136, 80.265], [32.24, 80.278], [32.723, 80.313], [32.889, 80.318], [33.066, 80.307], [33.235, 80.281], [33.291, 80.254], [33.455, 80.239], [33.491, 80.227], [33.47, 80.185], [33.355, 80.142], [32.237, 80.095], [32.0, 80.061]]}}, {"type": "Feature", "properties": {"id": 8076, "lvl": 0, "eu": "F", "efta": "T", "cc": "F", "oth": "F", "co": "T"}, "geometry": {"type": "LineString", "coordinates": [[26.077, 80.182], [26.022, 80.178], [26.011, 80.181], [26.024, 80.193], [26.034, 80.196], [26.077, 80.197], [26.104, 80.19], [26.097, 80.185], [26.077, 80.182]]}}, {"type": "Feature", "properties": {"id": 8086, "lvl": 0, "eu": "F", "efta": "T", "cc": "F", "oth": "F", "co": "T"}, "geometry": {"type": "LineString", "coordinates": [[26.165, 80.453], [26.148, 80.439], [26.124, 80.445], [26.147, 80.457], [26.165, 80.453]]}}, {"type": "Feature", "properties": {"id": 8087, "lvl": 0, "eu": "F", "efta": "T", "cc": "F", "oth": "F", "co": "T"}, "geometry": {"type": "LineString", "coordinates": [[25.991, 80.451], [25.978, 80.446], [25.958, 80.455], [25.976, 80.461], [25.991, 80.451]]}}, {"type": "Feature", "properties": {"id": 8030, "lvl": 0, "eu": "F", "efta": "T", "cc": "F", "oth": "F", "co": "T"}, "geometry": {"type": "LineString", "coordinates": [[20.961, 79.017], [20.944, 79.016], [20.937, 79.019], [20.939, 79.026], [20.935, 79.031], [20.957, 79.035], [20.981, 79.032], [20.986, 79.028], [20.961, 79.017]]}}, {"type": "Feature", "properties": {"id": 8031, "lvl": 0, "eu": "F", "efta": "T", "cc": "F", "oth": "F", "co": "T"}, "geometry": {"type": "LineString", "coordinates": [[21.098, 79.034], [21.091, 79.022], [21.077, 79.029], [21.091, 79.039], [21.098, 79.034]]}}, {"type": "Feature", "properties": {"id": 8032, "lvl": 0, "eu": "F", "efta": "T", "cc": "F", "oth": "F", "co": "T"}, "geometry": {"type": "LineString", "coordinates": [[21.151, 79.038], [21.142, 79.03], [21.125, 79.037], [21.14, 79.044], [21.151, 79.038]]}}, {"type": "Feature", "properties": {"id": 8035, "lvl": 0, "eu": "F", "efta": "T", "cc": "F", "oth": "F", "co": "T"}, "geometry": {"type": "LineString", "coordinates": [[20.175, 79.117], [20.32, 79.104], [20.507, 79.11], [20.708, 79.084], [20.741, 79.066], [20.641, 79.026], [20.321, 79.007], [20.148, 79.029], [20.104, 79.072], [20.175, 79.117]]}}, {"type": "Feature", "properties": {"id": 8034, "lvl": 0, "eu": "F", "efta": "T", "cc": "F", "oth": "F", "co": "T"}, "geometry": {"type": "LineString", "coordinates": [[19.87, 79.065], [19.859, 79.06], [19.844, 79.068], [19.859, 79.075], [19.87, 79.065]]}}, {"type": "Feature", "properties": {"id": 8038, "lvl": 0, "eu": "F", "efta": "T", "cc": "F", "oth": "F", "co": "T"}, "geometry": {"type": "LineString", "coordinates": [[20.14, 79.248], [20.124, 79.241], [20.105, 79.25], [20.126, 79.257], [20.14, 79.248]]}}, {"type": "Feature", "properties": {"id": 8039, "lvl": 0, "eu": "F", "efta": "T", "cc": "F", "oth": "F", "co": "T"}, "geometry": {"type": "LineString", "coordinates": [[20.225, 79.249], [20.214, 79.243], [20.202, 79.251], [20.213, 79.258], [20.225, 79.249]]}}, {"type": "Feature", "properties": {"id": 8040, "lvl": 0, "eu": "F", "efta": "T", "cc": "F", "oth": "F", "co": "T"}, "geometry": {"type": "LineString", "coordinates": [[19.995, 79.229], [19.968, 79.227], [19.939, 79.24], [19.995, 79.292], [20.036, 79.293], [20.1, 79.276], [20.046, 79.233], [19.995, 79.229]]}}, {"type": "Feature", "properties": {"id": 8042, "lvl": 0, "eu": "F", "efta": "T", "cc": "F", "oth": "F", "co": "T"}, "geometry": {"type": "LineString", "coordinates": [[21.087, 79.303], [21.059, 79.287], [21.032, 79.294], [21.067, 79.31], [21.087, 79.303]]}}, {"type": "Feature", "properties": {"id": 8043, "lvl": 0, "eu": "F", "efta": "T", "cc": "F", "oth": "F", "co": "T"}, "geometry": {"type": "LineString", "coordinates": [[21.132, 79.317], [21.121, 79.307], [21.107, 79.313], [21.12, 79.321], [21.132, 79.317]]}}, {"type": "Feature", "properties": {"id": 8044, "lvl": 0, "eu": "F", "efta": "T", "cc": "F", "oth": "F", "co": "T"}, "geometry": {"type": "LineString", "coordinates": [[19.176, 79.319], [19.165, 79.313], [19.148, 79.321], [19.164, 79.327], [19.176, 79.319]]}}, {"type": "Feature", "properties": {"id": 8048, "lvl": 0, "eu": "F", "efta": "T", "cc": "F", "oth": "F", "co": "T"}, "geometry": {"type": "LineString", "coordinates": [[19.513, 79.402], [19.502, 79.398], [19.489, 79.407], [19.501, 79.412], [19.513, 79.402]]}}, {"type": "Feature", "properties": {"id": 8049, "lvl": 0, "eu": "F", "efta": "T", "cc": "F", "oth": "F", "co": "T"}, "geometry": {"type": "LineString", "coordinates": [[19.578, 79.423], [19.55, 79.411], [19.489, 79.429], [19.53, 79.446], [19.578, 79.423]]}}, {"type": "Feature", "properties": {"id": 8050, "lvl": 0, "eu": "F", "efta": "T", "cc": "F", "oth": "F", "co": "T"}, "geometry": {"type": "LineString", "coordinates": [[18.749, 79.55], [18.737, 79.543], [18.722, 79.55], [18.738, 79.557], [18.749, 79.55]]}}, {"type": "Feature", "properties": {"id": 8051, "lvl": 0, "eu": "F", "efta": "T", "cc": "F", "oth": "F", "co": "T"}, "geometry": {"type": "LineString", "coordinates": [[19.323, 79.577], [19.312, 79.568], [19.297, 79.572], [19.312, 79.581], [19.323, 79.577]]}}, {"type": "Feature", "properties": {"id": 8062, "lvl": 0, "eu": "F", "efta": "T", "cc": "F", "oth": "F", "co": "T"}, "geometry": {"type": "LineString", "coordinates": [[18.025, 79.962], [18.009, 79.955], [18.0, 79.955], [17.992, 79.957], [17.983, 79.962], [17.991, 79.967], [18.0, 79.969], [18.01, 79.969], [18.025, 79.962]]}}, {"type": "Feature", "properties": {"id": 8064, "lvl": 0, "eu": "F", "efta": "T", "cc": "F", "oth": "F", "co": "T"}, "geometry": {"type": "LineString", "coordinates": [[18.336, 79.959], [18.31, 79.947], [18.139, 79.964], [18.284, 79.984], [18.336, 79.959]]}}, {"type": "Feature", "properties": {"id": 8063, "lvl": 0, "eu": "F", "efta": "T", "cc": "F", "oth": "F", "co": "T"}, "geometry": {"type": "LineString", "coordinates": [[18.54, 79.974], [18.529, 79.968], [18.513, 79.975], [18.528, 79.981], [18.54, 79.974]]}}, {"type": "Feature", "properties": {"id": 8065, "lvl": 0, "eu": "F", "efta": "T", "cc": "F", "oth": "F", "co": "T"}, "geometry": {"type": "LineString", "coordinates": [[18.595, 79.986], [18.583, 79.977], [18.565, 79.983], [18.581, 79.99], [18.595, 79.986]]}}, {"type": "Feature", "properties": {"id": 8067, "lvl": 0, "eu": "F", "efta": "T", "cc": "F", "oth": "F", "co": "T"}, "geometry": {"type": "LineString", "coordinates": [[18.376, 79.994], [18.402, 79.982], [18.434, 79.982], [18.442, 79.977], [18.437, 79.974], [18.39, 79.972], [18.376, 79.979], [18.356, 79.983], [18.338, 80.001], [18.346, 80.002], [18.376, 79.994]]}}, {"type": "Feature", "properties": {"id": 8045, "lvl": 0, "eu": "F", "efta": "T", "cc": "F", "oth": "F", "co": "T"}, "geometry": {"type": "LineString", "coordinates": [[20.66, 79.341], [20.648, 79.334], [20.632, 79.34], [20.648, 79.347], [20.66, 79.341]]}}, {"type": "Feature", "properties": {"id": 8046, "lvl": 0, "eu": "F", "efta": "T", "cc": "F", "oth": "F", "co": "T"}, "geometry": {"type": "LineString", "coordinates": [[20.609, 79.346], [20.601, 79.337], [20.587, 79.346], [20.601, 79.354], [20.609, 79.346]]}}, {"type": "Feature", "properties": {"id": 8047, "lvl": 0, "eu": "F", "efta": "T", "cc": "F", "oth": "F", "co": "T"}, "geometry": {"type": "LineString", "coordinates": [[20.046, 79.361], [20.124, 79.343], [20.137, 79.333], [20.126, 79.325], [20.091, 79.325], [19.995, 79.343], [19.958, 79.35], [19.681, 79.333], [19.634, 79.353], [19.651, 79.37], [19.643, 79.391], [19.662, 79.399], [19.809, 79.398], [19.995, 79.369], [20.046, 79.361]]}}, {"type": "Feature", "properties": {"id": 8055, "lvl": 0, "eu": "F", "efta": "T", "cc": "F", "oth": "F", "co": "T"}, "geometry": {"type": "LineString", "coordinates": [[19.804, 79.686], [19.773, 79.669], [19.743, 79.679], [19.782, 79.693], [19.804, 79.686]]}}, {"type": "Feature", "properties": {"id": 8078, "lvl": 0, "eu": "F", "efta": "T", "cc": "F", "oth": "F", "co": "T"}, "geometry": {"type": "LineString", "coordinates": [[21.162, 80.263], [21.145, 80.249], [21.134, 80.255], [21.156, 80.265], [21.162, 80.263]]}}, {"type": "Feature", "properties": {"id": 8079, "lvl": 0, "eu": "F", "efta": "T", "cc": "F", "oth": "F", "co": "T"}, "geometry": {"type": "LineString", "coordinates": [[21.222, 80.288], [21.205, 80.27], [21.186, 80.274], [21.205, 80.292], [21.222, 80.288]]}}, {"type": "Feature", "properties": {"id": 8084, "lvl": 0, "eu": "F", "efta": "T", "cc": "F", "oth": "F", "co": "T"}, "geometry": {"type": "LineString", "coordinates": [[21.354, 80.332], [21.306, 80.326], [21.284, 80.327], [21.278, 80.332], [21.288, 80.337], [21.304, 80.339], [21.308, 80.345], [21.412, 80.358], [21.418, 80.36], [21.423, 80.367], [21.443, 80.362], [21.438, 80.357], [21.44, 80.351], [21.435, 80.347], [21.354, 80.332]]}}, {"type": "Feature", "properties": {"id": 8088, "lvl": 0, "eu": "F", "efta": "T", "cc": "F", "oth": "F", "co": "T"}, "geometry": {"type": "LineString", "coordinates": [[20.189, 80.475], [20.173, 80.472], [20.153, 80.473], [20.144, 80.476], [20.151, 80.48], [20.178, 80.486], [20.189, 80.486], [20.2, 80.486], [20.207, 80.482], [20.202, 80.478], [20.189, 80.475]]}}, {"type": "Feature", "properties": {"id": 8091, "lvl": 0, "eu": "F", "efta": "T", "cc": "F", "oth": "F", "co": "T"}, "geometry": {"type": "LineString", "coordinates": [[20.294, 80.501], [20.261, 80.482], [20.217, 80.495], [20.261, 80.517], [20.294, 80.501]]}}, {"type": "Feature", "properties": {"id": 8092, "lvl": 0, "eu": "F", "efta": "T", "cc": "F", "oth": "F", "co": "T"}, "geometry": {"type": "LineString", "coordinates": [[19.995, 80.492], [19.919, 80.469], [19.853, 80.476], [19.812, 80.495], [19.851, 80.515], [19.976, 80.54], [19.995, 80.534], [20.046, 80.516], [20.049, 80.512], [19.995, 80.492]]}}, {"type": "Feature", "properties": {"id": 8066, "lvl": 0, "eu": "F", "efta": "T", "cc": "F", "oth": "F", "co": "T"}, "geometry": {"type": "LineString", "coordinates": [[18.04, 79.989], [18.029, 79.983], [18.014, 79.991], [18.028, 79.997], [18.04, 79.989]]}}, {"type": "Feature", "properties": {"id": 8068, "lvl": 0, "eu": "F", "efta": "T", "cc": "F", "oth": "F", "co": "T"}, "geometry": {"type": "LineString", "coordinates": [[18.66, 80.0], [18.647, 79.985], [18.619, 79.989], [18.636, 80.006], [18.645, 80.006], [18.66, 80.0]]}}, {"type": "Feature", "properties": {"id": 8070, "lvl": 0, "eu": "F", "efta": "T", "cc": "F", "oth": "F", "co": "T"}, "geometry": {"type": "LineString", "coordinates": [[18.087, 80.042], [18.097, 80.03], [18.076, 80.03], [18.055, 80.042], [18.061, 80.046], [18.082, 80.045], [18.087, 80.042]]}}, {"type": "Feature", "properties": {"id": 8077, "lvl": 0, "eu": "F", "efta": "T", "cc": "F", "oth": "F", "co": "T"}, "geometry": {"type": "LineString", "coordinates": [[18.803, 80.247], [18.793, 80.239], [18.778, 80.247], [18.792, 80.254], [18.803, 80.247]]}}, {"type": "Feature", "properties": {"id": 8083, "lvl": 0, "eu": "F", "efta": "T", "cc": "F", "oth": "F", "co": "T"}, "geometry": {"type": "LineString", "coordinates": [[18.574, 80.256], [18.435, 80.245], [18.145, 80.281], [18.1, 80.298], [18.161, 80.332], [18.31, 80.36], [18.533, 80.337], [18.649, 80.294], [18.574, 80.256]]}}, {"type": "Feature", "properties": {"id": 8081, "lvl": 0, "eu": "F", "efta": "T", "cc": "F", "oth": "F", "co": "T"}, "geometry": {"type": "LineString", "coordinates": [[18.752, 80.324], [18.745, 80.32], [18.72, 80.32], [18.715, 80.328], [18.737, 80.33], [18.752, 80.324]]}}, {"type": "Feature", "properties": {"id": 8093, "lvl": 0, "eu": "F", "efta": "T", "cc": "F", "oth": "F", "co": "T"}, "geometry": {"type": "LineString", "coordinates": [[19.789, 80.62], [19.772, 80.615], [19.754, 80.625], [19.773, 80.631], [19.789, 80.62]]}}, {"type": "Feature", "properties": {"id": 8094, "lvl": 0, "eu": "F", "efta": "T", "cc": "F", "oth": "F", "co": "T"}, "geometry": {"type": "LineString", "coordinates": [[20.787, 80.653], [20.708, 80.616], [20.565, 80.635], [20.533, 80.65], [20.602, 80.666], [20.77, 80.66], [20.787, 80.653]]}}, {"type": "Feature", "properties": {"id": 8095, "lvl": 0, "eu": "F", "efta": "T", "cc": "F", "oth": "F", "co": "T"}, "geometry": {"type": "LineString", "coordinates": [[21.299, 80.694], [21.129, 80.652], [21.065, 80.66], [21.037, 80.674], [21.105, 80.696], [21.278, 80.702], [21.299, 80.694]]}}, {"type": "Feature", "properties": {"id": 8096, "lvl": 0, "eu": "F", "efta": "T", "cc": "F", "oth": "F", "co": "T"}, "geometry": {"type": "LineString", "coordinates": [[20.968, 80.706], [20.844, 80.679], [20.766, 80.7], [20.65, 80.714], [20.579, 80.747], [20.627, 80.755], [20.787, 80.719], [20.948, 80.717], [20.968, 80.706]]}}, {"type": "Feature", "properties": {"id": 8097, "lvl": 0, "eu": "F", "efta": "T", "cc": "F", "oth": "F", "co": "T"}, "geometry": {"type": "LineString", "coordinates": [[20.445, 80.753], [20.434, 80.747], [20.419, 80.754], [20.434, 80.76], [20.445, 80.753]]}}, {"type": "Feature", "properties": {"id": 8098, "lvl": 0, "eu": "F", "efta": "T", "cc": "F", "oth": "F", "co": "T"}, "geometry": {"type": "LineString", "coordinates": [[20.375, 80.819], [20.361, 80.814], [20.347, 80.821], [20.361, 80.827], [20.375, 80.819]]}}]}