{"type":"Topology","bbox":[-6815988.488831432,1619632.4284475865,-6769456.545048501,1675234.2623677657],"transform":{"scale":[2.326713524822754,2.7802307075443355],"translate":[-6815988.488831432,1619632.4284475865]},"objects":{"nutsrg":{"type":"GeometryCollection","geometries":[{"type":"MultiPolygon","arcs":[[[8]],[[0]],[[3]],[[6]],[[4]],[[5]],[[9]],[[7]],[[2]],[[1]]],"properties":{"id":"FR","na":"FRANCE"}}]},"nutsbn":{"type":"GeometryCollection","geometries":[{"type":"LineString","arcs":[0],"properties":{"id":"22","lvl":0,"eu":"T","efta":"F","cc":"F","oth":"F","co":"T"}},{"type":"LineString","arcs":[1],"properties":{"id":"23","lvl":0,"eu":"T","efta":"F","cc":"F","oth":"F","co":"T"}},{"type":"LineString","arcs":[2],"properties":{"id":"24","lvl":0,"eu":"T","efta":"F","cc":"F","oth":"F","co":"T"}},{"type":"LineString","arcs":[3],"properties":{"id":"25","lvl":0,"eu":"T","efta":"F","cc":"F","oth":"F","co":"T"}},{"type":"LineString","arcs":[4],"properties":{"id":"26","lvl":0,"eu":"T","efta":"F","cc":"F","oth":"F","co":"T"}},{"type":"LineString","arcs":[5],"properties":{"id":"27","lvl":0,"eu":"T","efta":"F","cc":"F","oth":"F","co":"T"}},{"type":"LineString","arcs":[6],"properties":{"id":"28","lvl":0,"eu":"T","efta":"F","cc":"F","oth":"F","co":"T"}},{"type":"LineString","arcs":[7],"properties":{"id":"29","lvl":0,"eu":"T","efta":"F","cc":"F","oth":"F","co":"T"}},{"type":"LineString","arcs":[8],"properties":{"id":"31","lvl":0,"eu":"T","efta":"F","cc":"F","oth":"F","co":"T"}},{"type":"LineString","arcs":[9],"properties":{"id":"30","lvl":0,"eu":"T","efta":"F","cc":"F","oth":"F","co":"T"}}]},"cntrg":{"type":"GeometryCollection","geometries":[{"type":"MultiPolygon","arcs":[[[8]],[[0]],[[3]],[[6]],[[4]],[[5]],[[9]],[[7]],[[2]],[[1]]],"properties":{"id":"FR","na":"France"}}]},"cntbn":{"type":"GeometryCollection","geometries":[{"type":"LineString","arcs":[0],"properties":{"id":18182,"eu":"T","efta":"F","cc":"F","oth":"F","co":"T"}},{"type":"LineString","arcs":[1],"properties":{"id":18188,"eu":"T","efta":"F","cc":"F","oth":"F","co":"T"}},{"type":"LineString","arcs":[2],"properties":{"id":18300,"eu":"T","efta":"F","cc":"F","oth":"F","co":"T"}},{"type":"LineString","arcs":[3],"properties":{"id":18302,"eu":"T","efta":"F","cc":"F","oth":"F","co":"T"}},{"type":"LineString","arcs":[4],"properties":{"id":18309,"eu":"T","efta":"F","cc":"F","oth":"F","co":"T"}},{"type":"LineString","arcs":[5],"properties":{"id":18310,"eu":"T","efta":"F","cc":"F","oth":"F","co":"T"}},{"type":"LineString","arcs":[6],"properties":{"id":18312,"eu":"T","efta":"F","cc":"F","oth":"F","co":"T"}},{"type":"LineString","arcs":[7],"properties":{"id":18314,"eu":"T","efta":"F","cc":"F","oth":"F","co":"T"}},{"type":"LineString","arcs":[8],"properties":{"id":20031,"eu":"T","efta":"F","cc":"F","oth":"F","co":"T"}},{"type":"LineString","arcs":[9],"properties":{"id":19934,"eu":"T","efta":"F","cc":"F","oth":"F","co":"T"}}]},"gra":{"type":null}},"arcs":[[[19331,1411],[-101,-96],[-191,138],[263,116],[29,-158]],[[9188,1896],[-92,-37],[-171,109],[58,96],[198,-9],[7,-159]],[[10192,6292],[-248,-64],[-75,50],[43,87],[233,55],[47,-128]],[[18930,7093],[-291,-3],[188,202],[117,-39],[-14,-160]],[[18079,9055],[-58,-226],[-235,127],[198,124],[95,-25]],[[17697,9176],[-150,-19],[-121,75],[164,136],[92,0],[15,-192]],[[17990,9753],[116,-182],[126,27],[185,-93],[-230,-116],[-115,84],[-223,37],[141,243]],[[16519,9807],[-185,-161],[-153,209],[153,61],[38,-98],[147,-11]],[[3875,19999],[126,-72],[316,30],[190,-123],[267,9],[111,-21],[71,-42],[662,-197],[123,-75],[138,-1],[145,-121],[254,-34],[41,-112],[286,-249],[104,-48],[203,-7],[382,-267],[562,-165],[366,-330],[326,-58],[333,118],[192,-196],[444,-60],[-30,-247],[424,-169],[153,-435],[781,-82],[-99,-326],[335,-454],[479,-398],[299,-29],[-18,-218],[411,-414],[278,-221],[244,-707],[206,-112],[357,520],[425,309],[499,167],[620,-76],[1014,443],[456,333],[546,-204],[77,-599],[-243,17],[-294,269],[-442,-169],[221,-430],[-318,-283],[182,-227],[-192,-155],[-573,22],[-239,329],[-478,201],[-720,-93],[-189,-230],[-84,-663],[378,-332],[343,-10],[-173,-244],[59,-145],[366,33],[431,301],[62,-511],[216,-130],[259,14],[79,-174],[-227,-70],[-153,-212],[-288,61],[-507,-131],[-92,-341],[-348,117],[-282,-582],[714,-627],[256,72],[424,395],[240,-93],[117,126],[191,-107],[158,78],[210,-189],[201,219],[254,5],[-65,-476],[-392,-165],[-484,-87],[516,-528],[-119,-541],[979,-174],[-39,-239],[251,-332],[92,-429],[736,-131],[166,-217],[-39,-547],[213,-81],[251,-325],[442,18],[-202,-545],[312,-403],[-80,-233],[268,-271],[-381,-305],[-80,-239],[474,-112],[83,-553],[122,-191],[273,-80],[209,-475],[-160,-281],[-183,-59],[-131,129],[-121,-157],[194,-58],[234,-368],[-339,-273],[-169,-645],[-356,-260],[-170,-369],[-544,75],[348,-562],[-393,-64],[-448,-519],[-524,-98],[-292,61],[-438,369],[-349,608],[480,663],[-59,510],[346,19],[137,219],[308,58],[74,350],[-77,207],[-471,36],[-566,-385],[-482,-511],[-660,511],[54,323],[-1088,-244],[-1038,116],[-518,277],[-420,-159],[-382,564],[-143,-364],[-257,182],[-11,-439],[-369,90],[-235,338],[-291,-189],[-524,284],[-988,-295],[-292,-484],[-23,-72],[-93,-90],[-296,-131],[-255,44],[-182,112],[-90,137],[-134,265],[-566,156],[77,716],[-482,228],[254,232],[-25,191],[-708,171],[311,642],[261,144],[30,239],[476,326],[191,-12],[356,44],[694,575],[130,-140],[496,77],[-104,-446],[577,-274],[381,70],[283,-105],[583,214],[386,230],[-31,158],[288,-71],[-352,456],[-190,-3],[-482,83],[-117,356],[125,283],[-631,333],[18,217],[299,229],[-200,335],[60,281],[-211,34],[-279,-206],[-301,-49],[-156,-56],[72,-417],[-566,160],[-389,-129],[-142,218],[-455,89],[-958,-95],[-998,1061],[-282,73],[-841,252],[-78,64],[-197,340],[-478,229],[-149,287],[-655,803],[-800,1343],[244,1028],[122,383],[-125,307],[-904,742],[-337,491],[-421,108],[-595,874],[-122,773],[501,983],[696,695],[1151,509],[647,121],[321,41],[255,-34],[304,62]],[[16350,12487],[220,-120],[8,-64],[-309,-137],[-146,144],[-184,68],[116,96],[81,-62],[214,75]]]}
