{"type":"Topology","bbox":[-63.250023,13.732,-60.00111243349869,18.813],"transform":{"scale":[0.0001624536510076158,0.00025406270313515676],"translate":[-63.250023,13.732]},"objects":{"nutsrg0":{"type":"GeometryCollection","geometries":[{"type":"MultiPolygon","arcs":[[[0]],[[4]],[[3]],[[6]],[[5]],[[2]],[[1]],[[7]]],"properties":{"id":"FR","na":"France"}}]},"nutsbn0":{"type":"GeometryCollection","geometries":[{"type":"LineString","arcs":[0],"properties":{"id":5,"lvl":0,"eu":"T","efta":"F","cc":"F","oth":"F","co":"T"}},{"type":"LineString","arcs":[1],"properties":{"id":6,"lvl":0,"eu":"T","efta":"F","cc":"F","oth":"F","co":"T"}},{"type":"LineString","arcs":[2],"properties":{"id":7,"lvl":0,"eu":"T","efta":"F","cc":"F","oth":"F","co":"T"}},{"type":"LineString","arcs":[3],"properties":{"id":8,"lvl":0,"eu":"T","efta":"F","cc":"F","oth":"F","co":"T"}},{"type":"LineString","arcs":[4],"properties":{"id":9,"lvl":0,"eu":"T","efta":"F","cc":"F","oth":"F","co":"T"}},{"type":"LineString","arcs":[5],"properties":{"id":10,"lvl":0,"eu":"T","efta":"F","cc":"F","oth":"F","co":"T"}},{"type":"LineString","arcs":[6],"properties":{"id":11,"lvl":0,"eu":"T","efta":"F","cc":"F","oth":"F","co":"T"}},{"type":"LineString","arcs":[7],"properties":{"id":13,"lvl":0,"eu":"T","efta":"F","cc":"F","oth":"F","co":"T"}}]},"nutsrg1":{"type":"GeometryCollection","geometries":[{"type":"MultiPolygon","arcs":[[[0]],[[4]],[[3]],[[6]],[[5]],[[2]],[[1]],[[7]]],"properties":{"id":"FR9","na":"Départements d'outre-mer"}}]},"nutsbn1":{"type":"GeometryCollection","geometries":[{"type":"LineString","arcs":[0],"properties":{"id":5,"lvl":0,"eu":"T","efta":"F","cc":"F","oth":"F","co":"T"}},{"type":"LineString","arcs":[1],"properties":{"id":6,"lvl":0,"eu":"T","efta":"F","cc":"F","oth":"F","co":"T"}},{"type":"LineString","arcs":[2],"properties":{"id":7,"lvl":0,"eu":"T","efta":"F","cc":"F","oth":"F","co":"T"}},{"type":"LineString","arcs":[3],"properties":{"id":8,"lvl":0,"eu":"T","efta":"F","cc":"F","oth":"F","co":"T"}},{"type":"LineString","arcs":[4],"properties":{"id":9,"lvl":0,"eu":"T","efta":"F","cc":"F","oth":"F","co":"T"}},{"type":"LineString","arcs":[5],"properties":{"id":10,"lvl":0,"eu":"T","efta":"F","cc":"F","oth":"F","co":"T"}},{"type":"LineString","arcs":[6],"properties":{"id":11,"lvl":0,"eu":"T","efta":"F","cc":"F","oth":"F","co":"T"}},{"type":"LineString","arcs":[7],"properties":{"id":13,"lvl":0,"eu":"T","efta":"F","cc":"F","oth":"F","co":"T"}}]},"nutsrg2":{"type":"GeometryCollection","geometries":[{"type":"MultiPolygon","arcs":[[[4]],[[3]],[[6]],[[5]],[[2]],[[1]],[[8]],[[7]]],"properties":{"id":"FR91","na":"Guadeloupe"}},{"type":"Polygon","arcs":[[0]],"properties":{"id":"FR92","na":"Martinique"}}]},"nutsbn2":{"type":"GeometryCollection","geometries":[{"type":"LineString","arcs":[0],"properties":{"id":5,"lvl":0,"eu":"T","efta":"F","cc":"F","oth":"F","co":"T"}},{"type":"LineString","arcs":[1],"properties":{"id":6,"lvl":0,"eu":"T","efta":"F","cc":"F","oth":"F","co":"T"}},{"type":"LineString","arcs":[2],"properties":{"id":7,"lvl":0,"eu":"T","efta":"F","cc":"F","oth":"F","co":"T"}},{"type":"LineString","arcs":[3],"properties":{"id":8,"lvl":0,"eu":"T","efta":"F","cc":"F","oth":"F","co":"T"}},{"type":"LineString","arcs":[4],"properties":{"id":9,"lvl":0,"eu":"T","efta":"F","cc":"F","oth":"F","co":"T"}},{"type":"LineString","arcs":[5],"properties":{"id":10,"lvl":0,"eu":"T","efta":"F","cc":"F","oth":"F","co":"T"}},{"type":"LineString","arcs":[6],"properties":{"id":11,"lvl":0,"eu":"T","efta":"F","cc":"F","oth":"F","co":"T"}},{"type":"LineString","arcs":[8],"properties":{"id":12,"lvl":2,"eu":"T","efta":"F","cc":"F","oth":"F","co":"T"}},{"type":"LineString","arcs":[7],"properties":{"id":13,"lvl":0,"eu":"T","efta":"F","cc":"F","oth":"F","co":"T"}}]},"nutsrg3":{"type":"GeometryCollection","geometries":[{"type":"MultiPolygon","arcs":[[[4]],[[3]],[[6]],[[5]],[[2]],[[1]],[[8]],[[7]]],"properties":{"id":"FR910","na":"Guadeloupe"}},{"type":"Polygon","arcs":[[0]],"properties":{"id":"FR920","na":"Martinique"}}]},"nutsbn3":{"type":"GeometryCollection","geometries":[{"type":"LineString","arcs":[0],"properties":{"id":5,"lvl":0,"eu":"T","efta":"F","cc":"F","oth":"F","co":"T"}},{"type":"LineString","arcs":[1],"properties":{"id":6,"lvl":0,"eu":"T","efta":"F","cc":"F","oth":"F","co":"T"}},{"type":"LineString","arcs":[2],"properties":{"id":7,"lvl":0,"eu":"T","efta":"F","cc":"F","oth":"F","co":"T"}},{"type":"LineString","arcs":[3],"properties":{"id":8,"lvl":0,"eu":"T","efta":"F","cc":"F","oth":"F","co":"T"}},{"type":"LineString","arcs":[4],"properties":{"id":9,"lvl":0,"eu":"T","efta":"F","cc":"F","oth":"F","co":"T"}},{"type":"LineString","arcs":[5],"properties":{"id":10,"lvl":0,"eu":"T","efta":"F","cc":"F","oth":"F","co":"T"}},{"type":"LineString","arcs":[6],"properties":{"id":11,"lvl":0,"eu":"T","efta":"F","cc":"F","oth":"F","co":"T"}},{"type":"LineString","arcs":[8],"properties":{"id":12,"lvl":2,"eu":"T","efta":"F","cc":"F","oth":"F","co":"T"}},{"type":"LineString","arcs":[7],"properties":{"id":13,"lvl":0,"eu":"T","efta":"F","cc":"F","oth":"F","co":"T"}}]},"cntrg":{"type":"GeometryCollection","geometries":[{"type":"MultiPolygon","arcs":[[[9]],[[10]]],"properties":{"id":"AG","na":"ANTIGUA AND BARBUDA"}},{"type":"MultiPolygon","arcs":[[[12]],[[11]]],"properties":{"id":"AI","na":"ANGUILLA"}},{"type":"MultiPolygon","arcs":[[[13]],[[14]]],"properties":{"id":"AN","na":"NETHERLANDS ANTILLES"}},{"type":"Polygon","arcs":[[15]],"properties":{"id":"DM","na":"DOMINICA"}},{"type":"MultiPolygon","arcs":[[[16]],[[17]]],"properties":{"id":"KN","na":"SAINT KITTS AND NEVIS"}},{"type":"Polygon","arcs":[[18,22,19]],"properties":{"id":"LC","na":"SAINT LUCIA"}},{"type":"Polygon","arcs":[[20]],"properties":{"id":"MS","na":"MONTSERRAT"}},{"type":"Polygon","arcs":[[8]],"properties":{"id":"BL","na":"ST. BART'S"}}]},"cntbn":{"type":"GeometryCollection","geometries":[{"type":"LineString","arcs":[9],"properties":{"id":43,"cc":"F","oth":"T","co":"T"}},{"type":"LineString","arcs":[10],"properties":{"id":44,"cc":"F","oth":"T","co":"T"}},{"type":"LineString","arcs":[11],"properties":{"id":45,"cc":"F","oth":"T","co":"T"}},{"type":"LineString","arcs":[12],"properties":{"id":46,"cc":"F","oth":"T","co":"T"}},{"type":"LineString","arcs":[13],"properties":{"id":54,"cc":"F","oth":"T","co":"T"}},{"type":"LineString","arcs":[14],"properties":{"id":55,"cc":"F","oth":"T","co":"T"}},{"type":"LineString","arcs":[15],"properties":{"id":4406,"cc":"F","oth":"T","co":"T"}},{"type":"LineString","arcs":[16],"properties":{"id":7375,"cc":"F","oth":"T","co":"T"}},{"type":"LineString","arcs":[17],"properties":{"id":7376,"cc":"F","oth":"T","co":"T"}},{"type":"MultiLineString","arcs":[[18],[19]],"properties":{"id":7576,"cc":"F","oth":"T","co":"T"}},{"type":"LineString","arcs":[20],"properties":{"id":7856,"cc":"F","oth":"T","co":"T"}}]},"gra":{"type":"GeometryCollection","geometries":[{"type":"LineString","arcs":[21],"properties":{"id":"60W"}}]}},"arcs":[[[13522,2849],[-162,113],[-2,2],[-33,23],[-26,18],[-66,46],[-6,4],[8,10],[17,20],[31,38],[27,34],[8,1],[3,0],[20,2],[69,7],[197,19],[13,1],[269,26],[12,1],[12,1],[3,1],[-3,3],[-2,3],[-5,8],[-4,4],[-54,73],[-85,116],[-3,3],[-26,37],[-17,-2],[-6,-1],[-24,-2],[-1,0],[-63,-7],[-332,-34],[-19,12],[-6,4],[-8,5],[-122,76],[-23,15],[-7,4],[-176,110],[-89,56],[-10,6],[-13,8],[-51,221],[-6,26],[-1,4],[-7,31],[-1,5],[-182,169],[-131,122],[154,155],[1,1],[7,2],[55,14],[19,5],[7,2],[8,2],[6,2],[9,2],[111,29],[10,2],[252,-14],[30,-12],[5,-1],[204,-79],[258,-99],[160,-61],[252,-190],[78,-59],[11,-8],[40,-31],[20,15],[98,73],[13,10],[4,3],[1,0],[13,2],[4,0],[137,19],[5,1],[45,6],[11,1],[155,21],[-4,-4],[-3,-4],[-32,-41],[-4,-5],[-48,-60],[-14,-18],[-13,-17],[-11,-13],[-3,1],[-18,4],[-16,4],[-19,5],[-38,9],[-2,1],[-162,41],[-5,-60],[-1,-7],[-5,-50],[0,-9],[-4,-36],[-12,-136],[-1,-6],[-2,-20],[2,-2],[131,-98],[340,-254],[228,-170],[6,-5],[16,-12],[1,0],[1,-1],[2,-2],[86,-193],[-2,-3],[-33,-61],[-3,-5],[-9,-17],[-45,-83],[-1,-1],[-5,-4],[-7,-4],[-32,-21],[-23,-14],[-26,-16],[-24,-15],[-10,-6],[-140,-88],[-100,68],[-29,20],[-21,14],[25,28],[52,55],[17,18],[-39,10],[-57,13],[-21,5],[-63,16],[-160,21],[-15,2],[-25,4],[-11,1],[-61,8],[-38,5],[-5,1],[-17,2],[-15,2],[-36,5],[-52,7],[-42,6],[-1,0],[-15,2],[-16,2],[-80,11],[-17,2],[-82,11],[-178,-82],[0,-1],[-34,-15]],[[9938,8420],[3,-2],[25,-12],[3,-1],[37,-18],[36,-17],[26,-13],[-8,-4],[-6,-3],[-13,-6],[-47,-24],[-43,-22],[-14,4],[-2,1],[-19,6],[-34,10],[-28,8],[1,0],[54,61],[6,7],[17,18],[6,7]],[[10321,8470],[2,-2],[3,-3],[19,-21],[19,-21],[2,-2],[-5,-3],[-5,-3],[-4,-2],[-64,-39],[-25,-7],[-6,-2],[-1,-1],[-58,-18],[-9,3],[-34,7],[-39,9],[125,25],[12,3],[3,3],[17,20],[12,13],[4,4],[0,1],[28,32],[4,4]],[[12253,8420],[-445,116],[-34,149],[26,22],[1,2],[85,76],[6,5],[53,48],[4,4],[21,19],[19,17],[12,10],[7,6],[1,2],[1,1],[43,38],[5,4],[165,-7],[2,0],[4,0],[8,-4],[3,-2],[5,-3],[4,-2],[9,-6],[4,-2],[4,-2],[3,-2],[5,-3],[1,0],[159,-91],[6,-3],[4,-3],[5,-3],[10,-5],[13,-8],[20,-12],[2,-1],[8,-4],[44,-26],[51,-29],[18,-10],[-22,-173],[-8,-3],[-87,-30],[-245,-85]],[[13785,10305],[1,-3],[39,-66],[0,-1],[-1,0],[-6,-2],[-3,-1],[-6,-2],[-13,-5],[-5,-2],[-22,-8],[-1,0],[-200,-71],[-6,-1],[-43,-10],[-10,-3],[-5,-1],[-3,0],[-239,-55],[-11,-3],[0,2],[0,2],[-1,0],[-1,19],[0,1],[-2,26],[8,6],[37,27],[93,29],[1,0],[7,2],[5,1],[4,2],[1,0],[146,45],[9,2],[65,20],[9,3],[9,3],[17,5],[8,2],[15,5],[3,1],[5,1],[2,1],[10,3],[15,5],[26,7],[32,10],[1,1],[3,0],[7,3]],[[9691,8742],[-180,-14],[-26,27],[-2,3],[-133,144],[-2,2],[-3,3],[-1,1],[-56,61],[-36,39],[-98,106],[-5,5],[-11,12],[-4,5],[-14,15],[-8,8],[-2,10],[-2,6],[-112,410],[-2,9],[-80,295],[-4,14],[-1,3],[-3,12],[-1,2],[0,3],[-11,39],[-1,4],[-4,16],[4,26],[0,1],[14,77],[0,4],[6,30],[5,34],[3,15],[1,4],[1,1],[84,43],[139,71],[63,32],[50,25],[3,2],[8,3],[2,2],[5,-2],[19,-6],[11,-3],[34,-12],[52,-17],[19,-6],[332,-109],[35,-11],[102,-34],[4,-1],[26,-8],[37,-13],[10,-3],[40,-13],[10,-19],[23,-43],[1,-1],[3,-6],[3,-5],[10,-19],[1,-2],[17,-32],[56,5],[32,2],[106,9],[6,0],[133,11],[8,1],[7,0],[14,1],[5,1],[1,0],[34,2],[0,-3],[-2,-89],[0,-2],[0,-3],[-1,-29],[-1,-23],[0,-19],[0,-3],[0,-13],[-31,2],[-44,3],[-11,1],[-18,1],[-24,2],[-76,6],[-19,-73],[-4,-15],[-3,-9],[-15,-58],[-3,-11],[3,-7],[4,-11],[1,-4],[3,-7],[8,-19],[16,-42],[13,-32],[5,-13],[5,-12],[11,-29],[58,-146],[56,-143],[5,-11],[22,-58],[6,-14],[-1,0],[-8,-6],[-9,-6],[-15,-11],[-251,-183],[-4,-2],[-6,-5],[-38,-27],[-33,-24],[-192,-66],[-6,-3],[-66,-22],[-18,-7],[-94,-32]],[[11269,9753],[-23,0],[-18,-1],[-38,-1],[-20,0],[0,-1],[-3,0],[-428,-11],[-2,-1],[-3,0],[-7,0],[-6,4],[-41,30],[-3,3],[-48,34],[-44,32],[-113,82],[1,6],[1,3],[4,15],[2,6],[0,1],[4,15],[1,5],[1,4],[24,88],[5,19],[9,36],[1,3],[28,108],[106,31],[40,12],[5,1],[10,3],[15,4],[10,3],[13,4],[9,21],[0,1],[18,41],[7,16],[8,19],[3,7],[1,2],[4,10],[1,3],[-10,8],[-1,1],[-2,2],[-23,19],[-6,5],[-1,1],[-42,35],[-168,141],[-8,6],[-25,21],[137,68],[353,177],[2,-1],[123,-46],[2,-1],[83,-31],[4,-1],[4,-2],[33,-12],[8,-3],[3,-1],[6,-3],[36,-13],[14,-97],[2,-11],[27,-188],[2,-9],[5,-6],[175,-199],[0,-1],[2,-1],[14,-2],[1,-1],[11,-1],[5,-1],[18,-3],[24,-4],[2,0],[40,-6],[2,-1],[39,-6],[19,-3],[15,-2],[10,-2],[15,-2],[328,-52],[31,-4],[9,-2],[18,-3],[14,-11],[4,-3],[1,-1],[165,-132],[1,-1],[3,-2],[26,-21],[-499,-115],[-3,0],[-3,-1],[-37,-8],[-63,-15],[-212,-48],[-6,-2],[-41,-9],[-2,-1],[-61,-14],[-16,-3],[-52,-12],[-1,0],[-4,-1],[-3,-1],[-62,-14],[-19,-5]],[[1426,17022],[-203,20],[-3,0],[-44,4],[-2,0],[-25,3],[-153,-68],[5,47],[2,16],[1,8],[0,2],[1,6],[1,15],[1,4],[6,58],[0,2],[7,4],[24,11],[5,3],[8,4],[11,5],[13,7],[43,21],[4,2],[83,42],[4,1],[36,18],[51,25],[3,2],[13,0],[4,0],[18,-1],[12,-1],[54,-2],[7,0],[6,-1],[0,-1],[1,-40],[1,-17],[2,-82],[1,-43],[0,-14],[0,-7],[2,-53]],[[2351,16520],[1,-2],[1,-1],[7,-10],[6,-8],[1,-1],[10,-14],[1,-1],[1,0],[139,-56],[1,0],[25,-10],[2,0],[4,1],[18,4],[51,10],[12,3],[6,1],[6,6],[8,9],[13,13],[17,18],[1,0],[26,-12],[16,-8],[12,-6],[14,-6],[19,-10],[20,-9],[2,-1],[8,-4],[-3,-4],[-20,-30],[-201,-45],[-16,-4],[-38,-9],[-5,4],[-6,5],[-2,1],[-1,1],[-2,1],[-4,4],[-2,1],[-25,18],[-10,8],[-5,4],[-1,0],[-22,16],[-94,70],[-6,15],[-4,9],[-8,20],[27,9]],[[8802,13535],[546,-307],[319,19],[32,-204],[-363,-184],[-973,109],[-47,365],[486,202]],[[8606,15732],[119,-115],[-13,54],[34,-93],[199,58],[321,-233],[68,-160],[-109,-195],[-115,-31],[-382,201],[-191,-40],[34,240],[-171,202],[105,67],[122,-421],[151,165],[-43,119],[-173,45],[44,137]],[[893,17490],[-418,-22],[611,210],[24,86],[586,151],[-98,-192],[-705,-233]],[[1957,17972],[-189,-61],[26,55],[68,27],[95,-21]],[[1850,14746],[-138,-28],[-65,26],[-129,127],[34,91],[41,6],[93,-85],[193,-73],[-29,-64]],[[214,15332],[-214,-10],[9,88],[109,35],[100,-13],[24,-50],[-28,-50]],[[11436,7298],[481,-28],[392,-445],[-1,-715],[-133,-187],[-482,-135],[-177,22],[-145,542],[-501,731],[115,386],[262,-3],[189,-168]],[[4202,13269],[-220,-29],[-183,122],[129,315],[374,-82],[43,-220],[-143,-106]],[[3834,13757],[-175,-44],[-148,233],[-607,84],[-549,286],[112,164],[300,-1],[585,-276],[139,-211],[356,-151],[-13,-84]],[[14509,541],[96,-24],[-56,-190],[-260,-327]],[[13942,0],[-505,206],[32,510],[734,745],[144,-18],[275,-444],[-113,-458]],[[6590,11568],[-389,195],[248,381],[131,-27],[189,-279],[24,-180],[-203,-90]],[[19999,0],[0,1055],[0,1968],[0,1968],[0,1968],[0,1968],[0,1968],[0,1968],[0,1968],[0,1968],[0,1968],[0,1232]],[[14289,0],[-347,0]]]}
