{"type":"Topology","bbox":[90000,224000,436000,647000],"transform":{"scale":[17.300865043252163,21.151057552877646],"translate":[90000,224000]},"objects":{"nutsrg":{"type":"GeometryCollection","geometries":[{"type":"Polygon","arcs":[[0,1,2]],"properties":{"id":"FRY","na":"RUP FR - RÉGIONS ULTRAPÉRIPHÉRIQUES FRANÇAISES"}}]},"nutsbn":{"type":"GeometryCollection","geometries":[{"type":"LineString","arcs":[0,1],"properties":{"id":4,"lvl":0,"eu":"T","efta":"F","cc":"F","oth":"T","co":"F"}},{"type":"LineString","arcs":[2],"properties":{"id":5182,"lvl":0,"eu":"T","efta":"F","cc":"F","oth":"F","co":"T"}}]},"cntrg":{"type":"GeometryCollection","geometries":[{"type":"Polygon","arcs":[[3,-1,4,6]],"properties":{"id":"BR","na":"Brazil"}},{"type":"Polygon","arcs":[[-2,-4,7,5]],"properties":{"id":"SR","na":"Suriname"}}]},"cntbn":{"type":"GeometryCollection","geometries":[{"type":"LineString","arcs":[3],"properties":{"id":1365,"cc":"F","oth":"T","co":"F"}},{"type":"LineString","arcs":[4],"properties":{"id":1377,"cc":"F","oth":"T","co":"T"}},{"type":"LineString","arcs":[5],"properties":{"id":1692,"cc":"F","oth":"T","co":"T"}}]},"gra":{"type":null}},"arcs":[[[19493,10607],[-740,-432],[-200,-448],[-1091,-1010],[-1435,-2077],[-913,-751],[6,-456],[-1344,-2227],[53,-286],[-219,-432],[-629,-650],[-1168,-510],[-411,-461],[-730,-36],[-543,199],[-1026,-111],[188,315],[-575,412],[-1192,-449],[-1300,313],[-346,285],[-1016,-515],[-168,-266],[-707,-173],[-362,-342],[-447,253],[-772,-86],[-356,267],[-638,59],[-486,517],[-301,59]],[[625,1568],[467,111],[205,396],[631,316],[1129,1579],[218,892],[-145,1139],[855,784],[524,1455],[-540,382],[-300,575],[-405,142],[-622,649],[-453,659],[107,473],[-348,198],[-23,855],[-287,227],[121,1085],[-313,1603],[372,910],[2491,2297],[141,433]],[[4450,18728],[-6,337],[254,360],[843,-32],[2259,-839],[1577,-169],[1887,-512],[3654,-2677],[505,27],[871,-724],[1020,-528],[1128,-358],[731,-1695],[484,-637],[-164,-674]],[[0,1666],[625,-98]],[[19493,10607],[506,941]],[[3921,19999],[326,-83],[265,-381],[-210,-503],[148,-304]],[[19999,11548],[0,-11548],[-19999,0],[0,1666]],[[0,1666],[0,18333],[3921,0]]]}
