{"type": "FeatureCollection", "features": [{"type": "Feature", "properties": {"id": "6", "lvl": 0, "eu": "T", "efta": "F", "cc": "F", "oth": "F", "co": "T"}, "geometry": {"type": "LineString", "coordinates": [[-61.004, 14.808], [-60.952, 14.748], [-60.873, 14.772], [-60.946, 14.726], [-60.81, 14.481], [-60.858, 14.398], [-60.893, 14.42], [-60.866, 14.471], [-61.082, 14.47], [-61.088, 14.534], [-60.989, 14.549], [-61.019, 14.612], [-61.091, 14.6], [-61.151, 14.648], [-61.229, 14.822], [-61.18, 14.875], [-61.004, 14.808]]}}, {"type": "Feature", "properties": {"id": "7", "lvl": 0, "eu": "T", "efta": "F", "cc": "F", "oth": "F", "co": "T"}, "geometry": {"type": "LineString", "coordinates": [[-61.243, 15.875], [-61.332, 15.901], [-61.291, 16.003], [-61.195, 15.93], [-61.243, 15.875]]}}, {"type": "Feature", "properties": {"id": "9", "lvl": 0, "eu": "T", "efta": "F", "cc": "F", "oth": "F", "co": "T"}, "geometry": {"type": "LineString", "coordinates": [[-61.673, 16.325], [-61.612, 16.267], [-61.555, 16.285], [-61.59, 16.192], [-61.555, 16.053], [-61.697, 15.947], [-61.77, 16.059], [-61.806, 16.258], [-61.765, 16.354], [-61.673, 16.325]]}}, {"type": "Feature", "properties": {"id": "10", "lvl": 0, "eu": "T", "efta": "F", "cc": "F", "oth": "F", "co": "T"}, "geometry": {"type": "LineString", "coordinates": [[-61.255, 16.256], [-61.466, 16.197], [-61.527, 16.219], [-61.551, 16.287], [-61.509, 16.386], [-61.541, 16.438], [-61.464, 16.513], [-61.376, 16.341], [-61.258, 16.303], [-61.255, 16.256]]}}]}